azure_recommendations_6/__init__.py
azure_recommendations_6/recommendation/__init__.py
azure_recommendations_6/recommendation/advisor_recommendations.py
azure_recommendations_6/recommendation/network_recommendations.py
azure_recommendations_6/recommendation/utils.py
azure_recommendations_6/recommendation/vm_recommendations.py
azure_recommendations_6-0.1.5.dist-info/LICENCE
azure_recommendations_6-0.1.5.dist-info/METADATA
azure_recommendations_6-0.1.5.dist-info/WHEEL
azure_recommendations_6-0.1.5.dist-info/top_level.txt
azure_recommendations_6-0.1.5.dist-info/RECORD
